nexteraa_glue_jobs/ sedona-agg-logic-job.py
nexteraa_glue_jobs/base_job.py
nexteraa_glue_jobs/exceptions.py
nexteraa_glue_jobs/script.py
nexteraa_glue_jobs/sedona_job.py
nexteraa_glue_jobs/sedona_logic_job.py
nexteraa_glue_jobs/setup.py
nexteraa_glue_jobs/utilities.py
nnexteraa_glue-0.1.dev0.dist-info/METADATA
nnexteraa_glue-0.1.dev0.dist-info/WHEEL
nnexteraa_glue-0.1.dev0.dist-info/top_level.txt
nnexteraa_glue-0.1.dev0.dist-info/RECORD
